lektor_tags/__init__.py
lektor_tags/templates/lektor_tags_default_template.html
lektor_tags-0.5.2.dist-info/AUTHORS
lektor_tags-0.5.2.dist-info/LICENSE
lektor_tags-0.5.2.dist-info/METADATA
lektor_tags-0.5.2.dist-info/WHEEL
lektor_tags-0.5.2.dist-info/entry_points.txt
lektor_tags-0.5.2.dist-info/top_level.txt
lektor_tags-0.5.2.dist-info/RECORD
