Metadata-Version: 2.1
Name: lektor-tags
Version: 0.5.2
Summary: Lektor plugin to add tags.
Home-page: https://github.com/lektor/lektor-tags
Author: A. Jesse Jiryu Davis
Author-email: jesse@emptysquare.net
License: MIT
Keywords: Lektor,plugin,static-site,blog,tags
Classifier: Environment :: Plugins
Classifier: Environment :: Web Environment
Classifier: Framework :: Lektor
Classifier: Intended Audience :: Developers
Classifier: License :: OSI Approved :: MIT License
License-File: LICENSE
License-File: AUTHORS
Requires-Dist: importlib-resources >=5.10 ; python_version < "3.12"
Requires-Dist: dataclasses ; python_version < "3.7"
